scrapedict/__init__.py
scrapedict-0.3.1.dist-info/METADATA
scrapedict-0.3.1.dist-info/WHEEL
scrapedict-0.3.1.dist-info/top_level.txt
scrapedict-0.3.1.dist-info/RECORD
