Metadata-Version: 2.1
Name: scrapedict
Version: 0.3.1
Summary: Scrape HTML to dictionaries
Author-email: Pedro Rodrigues <me@pdbr.org>
Project-URL: homepage, https://github.com/medecau/scrapedict
Requires-Python: <4.0,>=3.8
Requires-Dist: beautifulsoup4 <5.0,>=4.4
Requires-Dist: parse <2.0,>=1.18
Requires-Dist: ftfy <7.0.0,>=6.1.1
Requires-Dist: normality <3.0.0,>=2.5.0
